<?xml version="1.0" encoding="utf-8" ?>
<LanguageData>

	<Cowgirl.label>Бурёнка</Cowgirl.label>

	<Cowgirl.corepart.parts.7.customlabel>left lung</Cowgirl.corepart.parts.7.customlabel>

	<Cowgirl.corepart.parts.8.customlabel>right lung</Cowgirl.corepart.parts.8.customlabel>

	<Cowgirl.corepart.parts.9.customlabel>left kidney</Cowgirl.corepart.parts.9.customlabel>

	<Cowgirl.corepart.parts.10.customlabel>right kidney</Cowgirl.corepart.parts.10.customlabel>

	<Cowgirl.corepart.parts.12.parts.0.parts.1.customlabel>left eye</Cowgirl.corepart.parts.12.parts.0.parts.1.customlabel>

	<Cowgirl.corepart.parts.12.parts.0.parts.2.customlabel>right eye</Cowgirl.corepart.parts.12.parts.0.parts.2.customlabel>

	<Cowgirl.corepart.parts.12.parts.0.parts.3.customlabel>left ear</Cowgirl.corepart.parts.12.parts.0.parts.3.customlabel>

	<Cowgirl.corepart.parts.12.parts.0.parts.4.customlabel>right ear</Cowgirl.corepart.parts.12.parts.0.parts.4.customlabel>

	<Cowgirl.corepart.parts.13.customlabel>left shoulder</Cowgirl.corepart.parts.13.customlabel>

	<Cowgirl.corepart.parts.13.parts.0.customlabel>left clavicle</Cowgirl.corepart.parts.13.parts.0.customlabel>

	<Cowgirl.corepart.parts.13.parts.1.customlabel>left arm</Cowgirl.corepart.parts.13.parts.1.customlabel>

	<Cowgirl.corepart.parts.13.parts.1.parts.0.customlabel>left humerus</Cowgirl.corepart.parts.13.parts.1.parts.0.customlabel>

	<Cowgirl.corepart.parts.13.parts.1.parts.1.customlabel>left radius</Cowgirl.corepart.parts.13.parts.1.parts.1.customlabel>

	<Cowgirl.corepart.parts.13.parts.1.parts.2.customlabel>left hand</Cowgirl.corepart.parts.13.parts.1.parts.2.customlabel>

	<Cowgirl.corepart.parts.13.parts.1.parts.2.parts.0.customlabel>left pinky</Cowgirl.corepart.parts.13.parts.1.parts.2.parts.0.customlabel>

	<Cowgirl.corepart.parts.13.parts.1.parts.2.parts.1.customlabel>left ring finger</Cowgirl.corepart.parts.13.parts.1.parts.2.parts.1.customlabel>

	<Cowgirl.corepart.parts.13.parts.1.parts.2.parts.2.customlabel>left middle finger</Cowgirl.corepart.parts.13.parts.1.parts.2.parts.2.customlabel>

	<Cowgirl.corepart.parts.13.parts.1.parts.2.parts.3.customlabel>left index finger</Cowgirl.corepart.parts.13.parts.1.parts.2.parts.3.customlabel>

	<Cowgirl.corepart.parts.13.parts.1.parts.2.parts.4.customlabel>left thumb</Cowgirl.corepart.parts.13.parts.1.parts.2.parts.4.customlabel>

	<Cowgirl.corepart.parts.14.customlabel>right shoulder</Cowgirl.corepart.parts.14.customlabel>

	<Cowgirl.corepart.parts.14.parts.0.customlabel>right clavicle</Cowgirl.corepart.parts.14.parts.0.customlabel>

	<Cowgirl.corepart.parts.14.parts.1.customlabel>right arm</Cowgirl.corepart.parts.14.parts.1.customlabel>

	<Cowgirl.corepart.parts.14.parts.1.parts.0.customlabel>right humerus</Cowgirl.corepart.parts.14.parts.1.parts.0.customlabel>

	<Cowgirl.corepart.parts.14.parts.1.parts.1.customlabel>right radius</Cowgirl.corepart.parts.14.parts.1.parts.1.customlabel>

	<Cowgirl.corepart.parts.14.parts.1.parts.2.customlabel>right hand</Cowgirl.corepart.parts.14.parts.1.parts.2.customlabel>

	<Cowgirl.corepart.parts.14.parts.1.parts.2.parts.0.customlabel>right pinky</Cowgirl.corepart.parts.14.parts.1.parts.2.parts.0.customlabel>

	<Cowgirl.corepart.parts.14.parts.1.parts.2.parts.1.customlabel>right ring finger</Cowgirl.corepart.parts.14.parts.1.parts.2.parts.1.customlabel>

	<Cowgirl.corepart.parts.14.parts.1.parts.2.parts.2.customlabel>right middle finger</Cowgirl.corepart.parts.14.parts.1.parts.2.parts.2.customlabel>

	<Cowgirl.corepart.parts.14.parts.1.parts.2.parts.3.customlabel>right index finger</Cowgirl.corepart.parts.14.parts.1.parts.2.parts.3.customlabel>

	<Cowgirl.corepart.parts.14.parts.1.parts.2.parts.4.customlabel>right thumb</Cowgirl.corepart.parts.14.parts.1.parts.2.parts.4.customlabel>

	<Cowgirl.corepart.parts.16.customlabel>left leg</Cowgirl.corepart.parts.16.customlabel>

	<Cowgirl.corepart.parts.16.parts.0.customlabel>left femur</Cowgirl.corepart.parts.16.parts.0.customlabel>

	<Cowgirl.corepart.parts.16.parts.1.customlabel>left tibia</Cowgirl.corepart.parts.16.parts.1.customlabel>

	<Cowgirl.corepart.parts.16.parts.2.customlabel>left hoof</Cowgirl.corepart.parts.16.parts.2.customlabel>

	<Cowgirl.corepart.parts.17.customlabel>right leg</Cowgirl.corepart.parts.17.customlabel>

	<Cowgirl.corepart.parts.17.parts.0.customlabel>right femur</Cowgirl.corepart.parts.17.parts.0.customlabel>

	<Cowgirl.corepart.parts.17.parts.1.customlabel>right tibia</Cowgirl.corepart.parts.17.parts.1.customlabel>

	<Cowgirl.corepart.parts.17.parts.2.customlabel>right hoof</Cowgirl.corepart.parts.17.parts.2.customlabel>

</LanguageData>
